{"\"developing nation\"": ["developing countries", "developing country", "Third World", "emerging nations", "developing nations", "least-developed countries", "less-developed countries", "LDCs", "countries, developing"], "\"ethnic group\"": ["ethnic groups", "ethnic group", "groups, ethnic"], "\"ethnic groups\"": ["ethnic groups", "ethnic group", "groups, ethnic"], "\"first nation\"": ["First Nations (culture)"], "\"first nations\"": ["First Nations (culture)"], "\"low-income country\"": ["developing countries", "developing country", "Third World", "emerging nations", "developing nations", "least-developed countries", "less-developed countries", "LDCs", "countries, developing"], "\"medicine man\"": ["shamans", "shaman", "shamans'", "shaman's", "medicine men", "medicine women", "men, medicine", "women, medicine"], "\"medicine men\"": ["shamans", "shaman", "shamans'", "shaman's", "medicine men", "medicine women", "men, medicine", "women, medicine"], "\"mixed race\"": ["multiracial", "multi-racial", "racially mixed", "mixed race", "multirace"], "\"torres strait\"": ["Torres Strait", "Torres Strait Islands"], "aboriginal": ["indigenous people", "indigenous person", "indigenous peoples", "aboriginal peoples", "indigenous populations", "native peoples", "aborigines", "indigenes", "people, indigenous"], "asian": ["Asian", "Oriental (Asian)"], "berber": ["Berber (culture or style)", "Berbers (cultures or styles)"], "black": ["Black (general, race and ethnicity)"], "caucasian": ["Caucasian (culture or style)"], "disabled": ["handicapped", "handicapped's", "disabled", "disabled people"], "dwarf": ["dwarfs", "dwarf", "dwarf's", "dwarfs'", "dwarves"], "enslaved": ["enslaved people", "enslaved person", "enslaved persons", "slaves (people)", "slave (person)", "slave's (person's )", "slaves' (peoples')", "people, enslaved"], "eskimo": ["Eskimo (culture or style)", "Eskimo Tradition"], "ethnicity": ["ethnicity", "ethnic", "ethnic group identity", "ethnic identity"], "gay": ["homosexuality", "homosexual (sexuality)", "gay (general homosexuality)", "queer (homosexual)"], "gypsy": ["Rom (culture)", "Roma (culture)", "Gypsy", "Gipsy"], "handicap": ["handicapped", "handicapped's", "disabled", "disabled people"], "hermaphrodite": ["hermaphrodites (people)", "intersex people", "intersexuals", "intersexual", "hermaphrodite (person)"], "homosexual": ["homosexuals (people)", "homosexual (person)"], "hottentot": ["Khoikhoi", "KhoiKhoi", "Khoi Khoi", "Khoikhoin", "Khoekhoe", "Khoi (Khoikhoi)", "Khoe", "Hottentot"], "immigrant": ["immigrants", "immigrant", "immigrant's", "immigrants'"], "indian": ["Native American", "American Indian", "Indian (Native American)", "American, Native", "Indian, American", "Native Americans"], "indigenous": ["indigenous people", "indigenous person", "indigenous peoples", "aboriginal peoples", "indigenous populations", "native peoples", "aborigines", "indigenes", "people, indigenous"], "indo": ["Indo-European (culture)", "Aryan (Indo-European culture)", "Arian (Indo-European culture)", "Indo-Germanic", "Japhetic"], "indo-european": ["Indo-European (culture)", "Aryan (Indo-European culture)", "Arian (Indo-European culture)", "Indo-Germanic", "Japhetic"], "intersex": ["hermaphrodites (people)", "intersex people", "intersexuals", "intersexual", "hermaphrodite (person)"], "inuit": ["Inuit (Canadian Arctic Native style)", "Canadian Eskimo", "Eskimo, Canadian"], "khoisan": ["Khoisan-speaking peoples styles", "Khoisan-speaking peoples style", "styles, Khoisan-speaking peoples"], "lgbt": ["LGBTQ+", "LGBT", "lesbian, gay, bisexual, and transgender", "lesbian, gay, bisexual, transgender/transsexual/transvestite", "L.G.B.T.Q.", "LGB", "GLBT", "LGBTQ"], "maroon": ["Maroon", "maroon"], "m\u00e9tis": ["Metis", "M\u00e9tis"], "mohammedan": ["Islam", "Islamic (religion)", "Islamism", "Mohammedan", "Mohammedanism", "Moslem", "Muhammadanism", "Muslim", "Muslimism", "Mussulmanism", "mahom\u00e9tanisme", "islamisme"], "moor": ["Maure", "Maures", "Moor (culture or style)", "Mauri (Arab-Berber culture or style)"], "muslim": ["Islam", "Islamic (religion)", "Islamism", "Mohammedan", "Mohammedanism", "Moslem", "Muhammadanism", "Muslim", "Muslimism", "Mussulmanism", "mahom\u00e9tanisme", "islamisme"], "native": ["indigenous people", "indigenous person", "indigenous peoples", "aboriginal peoples", "indigenous populations", "native peoples", "aborigines", "indigenes", "people, indigenous"], "negro": ["African American", "Afro-American", "Black (African American)", "Negro (African American)"], "oriental": ["Asian", "Oriental (Asian)"], "primitive": ["primitive art", "art, primitive"], "primitivism": ["primitivism (artistic concept)", "neoprimitivism", "neo-primitivism"], "pygmy": ["Pygmy (African culture or style)", "Pigmy (African culture or style)", "Bakola (Pygmy, culture or style)"], "queer": ["homosexuality", "homosexual (sexuality)", "gay (general homosexuality)", "queer (homosexual)"], "race": ["race (group of people)", "races (groups of people)", "peoples (races)"], "retarded": ["intellectually disabled", "developmentally disabled", "mentally retarded"], "roma": ["Rom (culture)", "Roma (culture)", "Gypsy", "Gipsy"], "servant": ["servants", "servant", "servant's", "servants'"], "slave": ["enslaved people", "enslaved person", "enslaved persons", "slaves (people)", "slave (person)", "slave's (person's )", "slaves' (peoples')", "people, enslaved"], "transvestite": ["LGBTQ+", "LGBT", "lesbian, gay, bisexual, and transgender", "lesbian, gay, bisexual, transgender/transsexual/transvestite", "L.G.B.T.Q.", "LGB", "GLBT", "LGBTQ"], "tribe": ["tribes (kinship groups)", "tribe (kinship group)", "tribal societies"]}